{
  "clients": [
    {
      "id": "1",
      "name": "Cliente1",
      "age": 25
    },
    {
      "id": "2",
      "name": "Cliente2",
      "age": 30
    },
    {
      "id": "3",
      "name": "Cliente3",
      "age": 26
    },
    {
      "id": "4",
      "name": "Cliente4",
      "age": 26
    },
    {
      "id": 5,
      "name": "asdsada",
      "age": "213",
      "email": "ksjdkadjksad"
    }
  ],
  "products": [
    {
      "code": "P001",
      "description": "Producto1",
      "price": 20,
      "id": "83bb"
    },
    {
      "code": "P002",
      "description": "Producto2",
      "price": 15.5,
      "id": "05f7"
    },
    {
      "id": 3,
      "code": "5",
      "description": "asdad",
      "price": "231"
    }
  ],
  "invoices": [
    {
      "id": "1",
      "date": "2024-02-23",
      "client": 1,
      "itemsInvoice": [
        {
          "product": "P001",
          "quantity": 2
        },
        {
          "product": "P002",
          "quantity": 1
        }
      ],
      "totalInvoice": 55.5
    },
    {
      "id": "2",
      "date": "2024-02-24",
      "client": 2,
      "itemsInvoice": [
        {
          "product": "P001",
          "quantity": 3
        },
        {
          "product": "P002",
          "quantity": 2
        }
      ],
      "totalInvoice": 86.5
    },
    {
      "id": "3",
      "date": "2024-02-24",
      "client": 3,
      "itemsInvoice": [
        {
          "product": "P001",
          "quantity": 3
        },
        {
          "product": "P002",
          "quantity": 2
        }
      ],
      "totalInvoice": 86.5
    },
    {
      "id": "4",
      "name": "Cliente4",
      "age": 26
    },
    {
      "id": "4",
      "date": "2024-02-23",
      "client": 4,
      "itemsInvoice": [
        {
          "product": "P001",
          "quantity": 2
        },
        {
          "product": "P002",
          "quantity": 1
        }
      ],
      "totalInvoice": 55.5
    },
    {
      "id": "5",
      "name": "juanito",
      "age": "33",
      "email": "ksjdkadjksad"
    },
    {
      "id": 7,
      "date": "33333-04-12",
      "items": [
        "asdad - Quantity: 44 - Total: 10164",
        "Producto2 - Quantity: 333 - Total: 5161.5",
        "Producto2 - Quantity: 3 - Total: 46.5"
      ],
      "total": 15371
    }
  ]
}